{
  "appPageId" : "0ee41af4-497c-401e-9f5e-748fa6c1ad72",
  "componentName" : "siteforce:sldsTwoCol84Layout",
  "id" : "d39a955e-6364-4615-884b-7dcd839e98e9",
  "label" : "Question Detail",
  "regions" : [ {
    "components" : [ {
      "componentAttributes" : {
        "bannerText" : "",
        "bannerTextWithKnowledge" : "Explore other <a href=\"javascript:void(0)\" class=\"headlineArticles\">articles</a> and <a href=\"javascript:void(0)\" class=\"headlineDiscussions\">discussions</a> on this topic.",
        "bannerTextWithoutKnowledge" : "Explore other <a href=\"javascript:void(0)\" class=\"headlineDiscussions\">discussions</a> on this topic.",
        "pageType" : "discussion",
        "showSubTopics" : true,
        "title" : "Welcome!",
        "uniqueNameOrId" : "{!recordId}"
      },
      "componentName" : "forceCommunity:headline",
      "id" : "0a348a16-64a4-45ef-84f7-238b93a55c10",
      "renderPriority" : "NEUTRAL",
      "renditionMap" : { },
      "type" : "component"
    } ],
    "id" : "baad376e-586b-4dd0-b50a-1a31c85b0b66",
    "regionName" : "header",
    "type" : "region"
  }, {
    "components" : [ {
      "componentAttributes" : {
        "id" : "{!feedItemId}"
      },
      "componentName" : "forceCommunity:feedItemDetail",
      "id" : "46c166a9-8de6-40ec-8b8f-a0be8aecbddd",
      "renderPriority" : "NEUTRAL",
      "renditionMap" : { },
      "type" : "component"
    } ],
    "id" : "a5e679c6-6cef-409b-8c75-939e367b166d",
    "regionName" : "content",
    "type" : "region"
  }, {
    "components" : [ {
      "componentAttributes" : {
        "numberOfItems" : 5,
        "showViewCounts" : true,
        "title" : "Related Questions"
      },
      "componentName" : "selfService:similarQuestions",
      "id" : "1df10931-c2c7-4887-9827-11cfcace2757",
      "renderPriority" : "NEUTRAL",
      "renditionMap" : { },
      "type" : "component"
    }, {
      "componentAttributes" : {
        "channel" : "DefaultChannel",
        "title" : ""
      },
      "componentName" : "forceCommunity:recommendations",
      "id" : "1c74b8c6-7c49-4481-8c00-21411800cb87",
      "renderPriority" : "NEUTRAL",
      "renditionMap" : { },
      "type" : "component"
    } ],
    "id" : "638edf79-c565-492b-a5bc-3f97cdeae1b1",
    "regionName" : "sidebar",
    "type" : "region"
  }, {
    "components" : [ {
      "componentAttributes" : {
        "askCommunityLabel" : "Ask a Question",
        "buttonBgColor" : "",
        "buttonBgHoverColor" : "",
        "buttonBorderColor" : "",
        "buttonRadius" : 0,
        "buttonTextColor" : "",
        "buttonTextHoverColor" : "",
        "buttonTwoBgColor" : "",
        "buttonTwoBgHoverColor" : "",
        "buttonTwoBorderColor" : "",
        "buttonTwoRadius" : 0,
        "buttonTwoTextColor" : "",
        "buttonTwoTextHoverColor" : "",
        "confirmationMessage" : "Got it!",
        "contactSupportLabel" : "Contact Support",
        "followUpPromptLabel" : "Can we close your question?",
        "headerLabel" : "Don't see what you're looking for?",
        "isAskFollowPromptEnabled" : true,
        "isIncludeArticlesEnabled" : false,
        "isIncludeDiscussionsEnabled" : true,
        "isInitialSatisfactionPromptEnabled" : true,
        "isPublisherDeflectionEnabled" : true,
        "maxSuggestions" : 5,
        "satisfactionPromptLabel" : "Did we help to answer your question?",
        "showDetails" : false,
        "showTopics" : true
      },
      "componentName" : "siteforce:napiliFooter",
      "id" : "5a78458a-34c2-4996-9347-2a5ec121ae9f",
      "renderPriority" : "NEUTRAL",
      "renditionMap" : { },
      "type" : "component"
    } ],
    "id" : "7d62f5bc-9f5f-466d-9ce6-d0f6ec052f51",
    "regionName" : "footer",
    "type" : "region"
  }, {
    "components" : [ {
      "componentAttributes" : {
        "customHeadTags" : "",
        "description" : "",
        "title" : "{!Record.Title}"
      },
      "componentName" : "forceCommunity:seoAssistant",
      "id" : "3d120091-e3e8-4a97-85d4-8a59abc23be8",
      "renditionMap" : { },
      "type" : "component"
    } ],
    "id" : "2314b761-5818-40fc-8128-3cd359eebd2e",
    "regionName" : "sfdcHiddenRegion",
    "type" : "region"
  } ],
  "themeLayoutType" : "Inner",
  "type" : "view",
  "viewType" : "feeditem"
}